XLMMacroDeobfuscator/__init__.py
XLMMacroDeobfuscator/boundsheet.py
XLMMacroDeobfuscator/deobfuscator.py
XLMMacroDeobfuscator/excel_wrapper.py
XLMMacroDeobfuscator/xlm-macro.lark.template
XLMMacroDeobfuscator/xls_wrapper.py
XLMMacroDeobfuscator/xls_wrapper_2.py
XLMMacroDeobfuscator/xlsb_wrapper.py
XLMMacroDeobfuscator/xlsm_wrapper.py
XLMMacroDeobfuscator/configs/__init__.py
XLMMacroDeobfuscator/configs/get_cell.conf
XLMMacroDeobfuscator/configs/get_window.conf
XLMMacroDeobfuscator/configs/get_workspace.conf
XLMMacroDeobfuscator/configs/settings.py
XLMMacroDeobfuscator-0.2.7.dist-info/LICENSE
XLMMacroDeobfuscator-0.2.7.dist-info/METADATA
XLMMacroDeobfuscator-0.2.7.dist-info/WHEEL
XLMMacroDeobfuscator-0.2.7.dist-info/entry_points.txt
XLMMacroDeobfuscator-0.2.7.dist-info/top_level.txt
XLMMacroDeobfuscator-0.2.7.dist-info/RECORD
