Metadata-Version: 2.1
Name: XLMMacroDeobfuscator
Version: 0.2.7
Summary: XLMMacroDeobfuscator is an XLM Emulation engine written in Python 3, designed to analyze and deobfuscate malicious XLM macros, also known as Excel 4.0 macros, contained in MS Excel files (XLS, XLSM, and XLSB).
Home-page: https://github.com/DissectMalware/XLMMacroDeobfuscator
Author: Amirreza Niakanlahiji
Author-email: aniak2@uis.edu
License: Apache License 2.0
Classifier: Development Status :: 4 - Beta
Classifier: Intended Audience :: Developers
Classifier: Intended Audience :: Information Technology
Classifier: Intended Audience :: Science/Research
Classifier: Intended Audience :: System Administrators
Classifier: License :: OSI Approved :: Apache Software License
Classifier: Natural Language :: English
Classifier: Operating System :: OS Independent
Classifier: Programming Language :: Python
Classifier: Programming Language :: Python :: 3
Classifier: Programming Language :: Python :: 3.4
Classifier: Programming Language :: Python :: 3.5
Classifier: Programming Language :: Python :: 3.6
Classifier: Programming Language :: Python :: 3.7
Classifier: Programming Language :: Python :: 3.8
Classifier: Topic :: Security
Classifier: Topic :: Software Development :: Libraries :: Python Modules
Requires-Python: >=3.4
License-File: LICENSE
Requires-Dist: pyxlsb2
Requires-Dist: lark-parser
Requires-Dist: xlrd2
Requires-Dist: untangle (==1.2.1)
Requires-Dist: msoffcrypto-tool
Requires-Dist: roman
Provides-Extra: secure
Requires-Dist: defusedxml ; extra == 'secure'
